payme/__init__.py
payme/admin.py
payme/apps.py
payme/auth.py
payme/constants.py
payme/exceptions.py
payme/models.py
payme/views.py
payme/__pycache__/__init__.cpython-311.pyc
payme/__pycache__/admin.cpython-311.pyc
payme/__pycache__/apps.cpython-311.pyc
payme/__pycache__/auth.cpython-311.pyc
payme/__pycache__/constants.cpython-311.pyc
payme/__pycache__/exceptions.cpython-311.pyc
payme/__pycache__/models.cpython-311.pyc
payme/__pycache__/views.cpython-311.pyc
payme/management/__init__.py
payme/management/__pycache__/__init__.cpython-311.pyc
payme/management/commands/__init__.py
payme/management/commands/create_payme_user.py
payme/management/commands/__pycache__/__init__.cpython-311.pyc
payme/management/commands/__pycache__/create_payme_user.cpython-311.pyc
payme/methods/__init__.py
payme/methods/__pycache__/__init__.cpython-311.pyc
payme/methods/merchant/__init__.py
payme/methods/merchant/helpers.py
payme/methods/merchant/serializers.py
payme/methods/merchant/validation_classes.py
payme/methods/merchant/views.py
payme/methods/merchant/__pycache__/__init__.cpython-311.pyc
payme/methods/merchant/__pycache__/serializers.cpython-311.pyc
payme/methods/merchant/__pycache__/validation_classes.cpython-311.pyc
payme/methods/merchant/__pycache__/views.cpython-311.pyc
payme/migrations/0001_initial.py
payme/migrations/0002_remove_transactionmodel_account_id_and_more.py
payme/migrations/__init__.py
payme/migrations/__pycache__/0001_initial.cpython-311.pyc
payme/migrations/__pycache__/0002_remove_transactionmodel_account_id_and_more.cpython-311.pyc
payme/migrations/__pycache__/__init__.cpython-311.pyc
payme_drf-1.0.0.dist-info/LICENSE
payme_drf-1.0.0.dist-info/METADATA
payme_drf-1.0.0.dist-info/WHEEL
payme_drf-1.0.0.dist-info/top_level.txt
payme_drf-1.0.0.dist-info/RECORD
