Metadata-Version: 2.1
Name: payme-drf
Version: 1.0.0
Summary: payme-drf
Home-page: https://github.com/islombeknv/payme-drf
Author: Islombek Normamatov
Author-email: islomjon2702@gmail.com
Classifier: Programming Language :: Python :: 3
Classifier: License :: OSI Approved :: MIT License
Requires-Python: >=3.5
License-File: LICENSE
Requires-Dist: requests
Requires-Dist: django
Requires-Dist: djangorestframework
